_pyspqr.abi3.so
pyspqr-0.2.0.dist-info/RECORD
pyspqr-0.2.0.dist-info/WHEEL
pyspqr-0.2.0.dist-info/COPYING
pyspqr-0.2.0.dist-info/top_level.txt
pyspqr-0.2.0.dist-info/METADATA
pyspqr/pyspqr.py
pyspqr/__init__.py
pyspqr/tests/test_extension.py
pyspqr/tests/__init__.py
pyspqr/tests/test_pyspqr.py
pyspqr/tests/__main__.py
pyspqr/.dylibs/libspqr.4.3.4.dylib
pyspqr/.dylibs/libcholmod.5.3.0.dylib
pyspqr/.dylibs/libsuitesparseconfig.7.8.3.dylib
pyspqr/.dylibs/libcamd.3.3.3.dylib
pyspqr/.dylibs/libccolamd.3.3.4.dylib
pyspqr/.dylibs/libcolamd.3.3.4.dylib
pyspqr/.dylibs/libamd.3.3.3.dylib
