Metadata-Version: 2.1
Name: pyspqr
Version: 0.2.0
Summary: Python bindings for SuiteSparseQR.
Author: Enzo Busseti
Maintainer-email: Enzo Busseti <enzo.busseti@gmail.com>
License: GPLv3
Project-URL: Repository, https://github.com/enzbus/pyspqr
License-File: COPYING
Requires-Dist: numpy
Requires-Dist: scipy
Provides-Extra: dev
Requires-Dist: build; extra == "dev"
Requires-Dist: twine; extra == "dev"
Requires-Dist: auditwheel; extra == "dev"
Requires-Dist: rstcheck; extra == "dev"
Requires-Dist: wheel; extra == "dev"
Requires-Dist: abi3audit; extra == "dev"
Requires-Dist: autopep8; extra == "dev"
